wealth/__init__.py
wealth/aligned_umap_analysis.py
wealth/animation.py
wealth/dacc.py
wealth/util.py
wealth-0.0.5.dist-info/LICENSE
wealth-0.0.5.dist-info/METADATA
wealth-0.0.5.dist-info/WHEEL
wealth-0.0.5.dist-info/top_level.txt
wealth-0.0.5.dist-info/RECORD
