Metadata-Version: 2.1
Name: wealth
Version: 0.0.5
Summary: Visualizing financial relations and evolutions
Home-page: https://github.com/thorwhalen/wealth
Author: Thor Whalen
License: apache-2.0
Platform: any
Requires-Dist: matplotlib
Requires-Dist: numpy
Requires-Dist: pandas
Requires-Dist: celluloid
Requires-Dist: importlib-resources
Requires-Dist: py2store
Requires-Dist: lined
Requires-Dist: argh
Requires-Dist: graze
